<annotation>
	<folder>mohan_dataset</folder>
	<filename>16.jpg</filename>
	<path>/home/mohandass/Desktop/mohan_dataset/16.jpg</path>
	<source>
		<database>Unknown</database>
	</source>
	<size>
		<width>540</width>
		<height>960</height>
		<depth>3</depth>
	</size>
	<segmented>0</segmented>
	<object>
		<name>mohan</name>
		<pose>Unspecified</pose>
		<truncated>0</truncated>
		<difficult>0</difficult>
		<bndbox>
			<xmin>247</xmin>
			<ymin>295</ymin>
			<xmax>407</xmax>
			<ymax>487</ymax>
		</bndbox>
	</object>
</annotation>
